sedona/__init__.py
sedona/__main__.py
sedona/cli.py
sedona/converter.py
sedona/description.py
sedona/playlist.py
sedona/version.py
sedona/video.py
sedona-1.0.4.dist-info/LICENSE
sedona-1.0.4.dist-info/METADATA
sedona-1.0.4.dist-info/WHEEL
sedona-1.0.4.dist-info/entry_points.txt
sedona-1.0.4.dist-info/top_level.txt
sedona-1.0.4.dist-info/RECORD
