Metadata-Version: 2.1
Name: sedona
Version: 1.0.4
Summary: Sedona is a free YouTube & YT Music mp3 downloader for songs.
Home-page: https://github.com/giovcandido/sedona
Author: Giovani Candido, Davi Neves
Author-email: giovcandido@outlook.com, davivirgula@gmail.com
License: GNU General Public License v3.0
Platform: UNKNOWN
Classifier: Development Status :: 5 - Production/Stable
Classifier: Programming Language :: Python :: 3.8
Classifier: Environment :: Console
Classifier: Operating System :: OS Independent
Classifier: Natural Language :: English
Classifier: Topic :: Multimedia :: Sound/Audio
Classifier: Topic :: Utilities
Classifier: License :: OSI Approved :: GNU General Public License v3 (GPLv3)
Requires-Python: >=3.8
License-File: LICENSE
